{
    "article_amount": 2,
    "article_id": {
        "class00001": {
            "article_id": "class00001",
            "article_img_url":
            "https://ik.imagekit.io/csiejarimgstorage/web_v2/article/user-7ea779b7-413a-477c-a920-895a0a8373f3_JeG2C96Fd.png",
            "article_link": "/article/class00001",
            "article_owner_id": "user-7ea779b7-413a-477c-a920-895a0a8373f3",
            "article_owner_img":
            "https://lh3.googleusercontent.com/a-/AFdZucoELGpfvy4rni6TLkSAfLk5E7wY8bQjIRY_VZqcmg=s96-c",
            "article_owner_name": "\u5353\u5bb6\u777f",
            "article_type": "class",
            "big_img_url": "",
            "content": "<p>test123456</p>",
            "create_time": "Sat, 23 Jul 2022 09:18:47 GMT",
            "home_delete_time": "2022-07-24",
            "home_img_delete_time": "2022-07-24",
            "ischeck": "true",
            "ishome": "true",
            "ishome_img": "false",
            "last_edit_time": "Sat, 23 Jul 2022 09:18:47 GMT",
            "last_editor_id": "user-7ea779b7-413a-477c-a920-895a0a8373f3",
            "last_editor_name": "\u5353\u5bb6\u777f",
            "subject": "title",
            "user_token": "token-a0047fe7-5d0f-4043-9b80-98155cd6c583"
        },
        "class00002": {
            "article_id": "class00002",
            "article_img_url": "",
            "article_link": "/article/class00002",
            "article_owner_id": "user-7ea779b7-413a-477c-a920-895a0a8373f3",
            "article_owner_img":
            "https://lh3.googleusercontent.com/a-/AFdZucoELGpfvy4rni6TLkSAfLk5E7wY8bQjIRY_VZqcmg=s96-c",
            "article_owner_name": "\u5353\u5bb6\u777f",
            "article_type": "class",
            "big_img_url":
            "https://ik.imagekit.io/csiejarimgstorage/web_v2/article/user-7ea779b7-413a-477c-a920-895a0a8373f3_0moBHdCgq.png",
            "content": "<p>12345679</p>",
            "create_time": "Sat, 23 Jul 2022 09:41:33 GMT",
            "home_delete_time": "",
            "home_img_delete_time": "2022-07-24",
            "ischeck": "false",
            "ishome": "false",
            "ishome_img": "true",
            "last_edit_time": "Sat, 23 Jul 2022 09:41:33 GMT",
            "last_editor_id": "user-7ea779b7-413a-477c-a920-895a0a8373f3",
            "last_editor_name": "\u5353\u5bb6\u777f",
            "subject": "title",
            "user_token": "token-b8ebca50-d945-452e-989e-49170892a719"
        }
    },
    "article_type": {
        "class": "\u73ed\u7d1a",
        "news": "\u516c\u544a",
        "project": "\u4f5c\u54c1",
        "resources": "\u8cc7\u6e90"
    }
}
